MyCLib1.cp36-win_amd64.pyd
MyCLib1-3.0.7.dist-info/DESCRIPTION.rst
MyCLib1-3.0.7.dist-info/METADATA
MyCLib1-3.0.7.dist-info/RECORD
MyCLib1-3.0.7.dist-info/WHEEL
MyCLib1-3.0.7.dist-info/metadata.json
MyCLib1-3.0.7.dist-info/top_level.txt
