Metadata-Version: 2.0
Name: MyCLib1
Version: 3.0.7
Summary: This is my MyCLib1 Extension
Home-page: UNKNOWN
Author: Sathyanesh Krishnan
Author-email: UNKNOWN
License: Apache License 2.0
Platform: UNKNOWN
